dh5bp/__init__.py
dh5bp/urls.py
dh5bp/views.py
dh5bp/static/css/dh5bp/main.css
dh5bp/static/css/dh5bp/normalize.css
dh5bp/static/img/dh5bp/apple-touch-icon-114x114-precomposed.png
dh5bp/static/img/dh5bp/apple-touch-icon-144x144-precomposed.png
dh5bp/static/img/dh5bp/apple-touch-icon-57x57-precomposed.png
dh5bp/static/img/dh5bp/apple-touch-icon-72x72-precomposed.png
dh5bp/static/img/dh5bp/apple-touch-icon-precomposed.png
dh5bp/static/img/dh5bp/apple-touch-icon.png
dh5bp/static/img/dh5bp/favicon.ico
dh5bp/static/js/dh5bp/main.js
dh5bp/static/js/dh5bp/plugins.js
dh5bp/static/js/dh5bp/vendor/jquery-1.10.2.min.js
dh5bp/static/js/dh5bp/vendor/modernizr-2.6.2.min.js
dh5bp/templates/dh5bp/404.html
dh5bp/templates/dh5bp/500.html
dh5bp/templates/dh5bp/base.html
dh5bp/templates/dh5bp/base_script_in_head.html
dh5bp/templates/dh5bp/crossdomain.xml
dh5bp/templates/dh5bp/humans.txt
dh5bp/templates/dh5bp/index.html
dh5bp/templates/dh5bp/js.html
dh5bp/templates/dh5bp/robots.txt
django_html5_boilerplate-1.0.8.dist-info/DESCRIPTION.rst
django_html5_boilerplate-1.0.8.dist-info/METADATA
django_html5_boilerplate-1.0.8.dist-info/pydist.json
django_html5_boilerplate-1.0.8.dist-info/RECORD
django_html5_boilerplate-1.0.8.dist-info/top_level.txt
django_html5_boilerplate-1.0.8.dist-info/WHEEL
